{
  "generator-jhipster": {
    "authenticationType": "jwt",
    "cacheProvider": "no",
    "serverPort": "8082",
    "serviceDiscoveryType": "eureka",
    "skipUserManagement": true,
    "baseName": "notification",
    "buildTool": "gradle",
    "databaseType": "mongodb",
    "devDatabaseType": "mongodb",
    "enableHibernateCache": false,
    "enableSwaggerCodegen": false,
    "enableTranslation": true,
    "jhiPrefix": "jhi",
    "languages": ["en", "vi"],
    "messageBroker": false,
    "nativeLanguage": "vi",
    "prodDatabaseType": "mongodb",
    "searchEngine": false,
    "skipClient": true,
    "testFrameworks": [],
    "websocket": false,
    "applicationType": "microservice",
    "packageName": "com.mycompany.store",
    "packageFolder": "com/mycompany/store",
    "jhipsterVersion": "6.10.5",
    "creationTimestamp": 1637766480851,
    "clientPackageManager": "npm",
    "jwtSecretKey": "ZGQ1Y2EwYTFmYTRiZmY3MGQ0MWM2MWVmMzQzMTRmYmFkMWRhMjk1MTJlMTAyMzI0MDJhMTY0NjE3ZDE2MWQyNjMxYmI3ZjNjYTEzODgwYjE4NWUyYzcwZWZmMGUxZWYwZDViNjEwZGE5NGIzN2RhNjgwOWMyMDY1MDU0YjAxZmI=",
    "embeddableLaunchScript": false,
    "entitySuffix": "",
    "dtoSuffix": "DTO",
    "otherModules": [],
    "blueprints": []
  },
  "entities": ["Notification"]
}
